<?xml version="1.0" encoding="UTF-8"?>
<Dictionary>
  <Classes>
    <Class>
      <Id>0</Id>
      <Name>Базовый</Name>
      <ParentIds />
      <Properties />
    </Class>
  </Classes>
  <Templates>
    <Template>
      <Id>1</Id>
      <ClassIds>
        <Id>0</Id>
      </ClassIds>
      <Propeties />
      <MatchMode>AbsoluteMeaningful</MatchMode>
      <Name>СО&#x20;РАН</Name>
      <MatchCases>
        <MatchCase>
          <Items>
            <MatchCaseItem type="TemplateReference">
              <TemplateReference>
                <Repeat>
                  <Minimum>1</Minimum>
                  <Maximum>1</Maximum>
                </Repeat>
                <ReferencesId>2</ReferencesId>
              </TemplateReference>
            </MatchCaseItem>
            <MatchCaseItem type="Block">
              <Block>
                <Repeat>
                  <Minimum>1</Minimum>
                  <Maximum>1</Maximum>
                </Repeat>
                <CaseSensitive>false</CaseSensitive>
                <LexemType>SpaceSymbol</LexemType>
                <Items>
                  <BlockItem type="AnySymbol">
                    <AnySymbol>
                      <LexemType>SpaceSymbol</LexemType>
                      <TimesMinimum>0</TimesMinimum>
                      <TimesMaximum>2000000000</TimesMaximum>
                    </AnySymbol>
                  </BlockItem>
                </Items>
              </Block>
            </MatchCaseItem>
            <MatchCaseItem type="TemplateReference">
              <TemplateReference>
                <Repeat>
                  <Minimum>1</Minimum>
                  <Maximum>1</Maximum>
                </Repeat>
                <ReferencesId>3</ReferencesId>
              </TemplateReference>
            </MatchCaseItem>
          </Items>
        </MatchCase>
      </MatchCases>
    </Template>
    <Template>
      <Id>2</Id>
      <ClassIds>
        <Id>1000000000</Id>
      </ClassIds>
      <Propeties />
      <MatchMode>AbsoluteMeaningful</MatchMode>
      <Name>СО</Name>
      <MatchCases>
        <MatchCase>
          <Items>
            <MatchCaseItem type="Block">
              <Block>
                <Repeat>
                  <Minimum>1</Minimum>
                  <Maximum>1</Maximum>
                </Repeat>
                <Tail>
                  <MaximumLength>2000000000</MaximumLength>
                  <MinimumLength>0</MinimumLength>
                </Tail>
                <CaseSensitive>false</CaseSensitive>
                <LexemType>RussianLetter</LexemType>
                <Items>
                  <BlockItem type="ExactString">
                    <ExactString>
                      <LexemType>RussianLetter</LexemType>
                      <Value>Сибирск</Value>
                    </ExactString>
                  </BlockItem>
                </Items>
              </Block>
            </MatchCaseItem>
            <MatchCaseItem type="Block">
              <Block>
                <Repeat>
                  <Minimum>1</Minimum>
                  <Maximum>1</Maximum>
                </Repeat>
                <CaseSensitive>false</CaseSensitive>
                <LexemType>SpaceSymbol</LexemType>
                <Items>
                  <BlockItem type="AnySymbol">
                    <AnySymbol>
                      <LexemType>SpaceSymbol</LexemType>
                      <TimesMinimum>0</TimesMinimum>
                      <TimesMaximum>2000000000</TimesMaximum>
                    </AnySymbol>
                  </BlockItem>
                </Items>
              </Block>
            </MatchCaseItem>
            <MatchCaseItem type="Block">
              <Block>
                <Repeat>
                  <Minimum>1</Minimum>
                  <Maximum>1</Maximum>
                </Repeat>
                <Tail>
                  <MaximumLength>2000000000</MaximumLength>
                  <MinimumLength>0</MinimumLength>
                </Tail>
                <CaseSensitive>false</CaseSensitive>
                <LexemType>RussianLetter</LexemType>
                <Items>
                  <BlockItem type="ExactString">
                    <ExactString>
                      <LexemType>RussianLetter</LexemType>
                      <Value>отделен</Value>
                    </ExactString>
                  </BlockItem>
                </Items>
              </Block>
            </MatchCaseItem>
          </Items>
        </MatchCase>
        <MatchCase>
          <Items>
            <MatchCaseItem type="Block">
              <Block>
                <Repeat>
                  <Minimum>1</Minimum>
                  <Maximum>1</Maximum>
                </Repeat>
                <CaseSensitive>false</CaseSensitive>
                <LexemType>RussianLetter</LexemType>
                <Items>
                  <BlockItem type="ExactString">
                    <ExactString>
                      <LexemType>RussianLetter</LexemType>
                      <Value>СО</Value>
                    </ExactString>
                  </BlockItem>
                </Items>
              </Block>
            </MatchCaseItem>
          </Items>
        </MatchCase>
      </MatchCases>
    </Template>
    <Template>
      <Id>3</Id>
      <ClassIds>
        <Id>0</Id>
      </ClassIds>
      <Propeties />
      <MatchMode>AbsoluteMeaningful</MatchMode>
      <Name>РАН</Name>
      <MatchCases>
        <MatchCase>
          <Items>
            <MatchCaseItem type="Block">
              <Block>
                <Repeat>
                  <Minimum>1</Minimum>
                  <Maximum>1</Maximum>
                </Repeat>
                <Tail>
                  <MaximumLength>2000000000</MaximumLength>
                  <MinimumLength>0</MinimumLength>
                </Tail>
                <CaseSensitive>false</CaseSensitive>
                <LexemType>RussianLetter</LexemType>
                <Items>
                  <BlockItem type="ExactString">
                    <ExactString>
                      <LexemType>RussianLetter</LexemType>
                      <Value>Российск</Value>
                    </ExactString>
                  </BlockItem>
                </Items>
              </Block>
            </MatchCaseItem>
            <MatchCaseItem type="Block">
              <Block>
                <Repeat>
                  <Minimum>1</Minimum>
                  <Maximum>1</Maximum>
                </Repeat>
                <CaseSensitive>false</CaseSensitive>
                <LexemType>SpaceSymbol</LexemType>
                <Items>
                  <BlockItem type="AnySymbol">
                    <AnySymbol>
                      <LexemType>SpaceSymbol</LexemType>
                      <TimesMinimum>0</TimesMinimum>
                      <TimesMaximum>2000000000</TimesMaximum>
                    </AnySymbol>
                  </BlockItem>
                </Items>
              </Block>
            </MatchCaseItem>
            <MatchCaseItem type="Block">
              <Block>
                <Repeat>
                  <Minimum>1</Minimum>
                  <Maximum>1</Maximum>
                </Repeat>
                <Tail>
                  <MaximumLength>2000000000</MaximumLength>
                  <MinimumLength>0</MinimumLength>
                </Tail>
                <CaseSensitive>false</CaseSensitive>
                <LexemType>RussianLetter</LexemType>
                <Items>
                  <BlockItem type="ExactString">
                    <ExactString>
                      <LexemType>RussianLetter</LexemType>
                      <Value>академ</Value>
                    </ExactString>
                  </BlockItem>
                </Items>
              </Block>
            </MatchCaseItem>
            <MatchCaseItem type="Block">
              <Block>
                <Repeat>
                  <Minimum>1</Minimum>
                  <Maximum>1</Maximum>
                </Repeat>
                <CaseSensitive>false</CaseSensitive>
                <LexemType>SpaceSymbol</LexemType>
                <Items>
                  <BlockItem type="AnySymbol">
                    <AnySymbol>
                      <LexemType>SpaceSymbol</LexemType>
                      <TimesMinimum>0</TimesMinimum>
                      <TimesMaximum>2000000000</TimesMaximum>
                    </AnySymbol>
                  </BlockItem>
                </Items>
              </Block>
            </MatchCaseItem>
            <MatchCaseItem type="Block">
              <Block>
                <Repeat>
                  <Minimum>1</Minimum>
                  <Maximum>1</Maximum>
                </Repeat>
                <Tail>
                  <MaximumLength>2000000000</MaximumLength>
                  <MinimumLength>0</MinimumLength>
                </Tail>
                <CaseSensitive>false</CaseSensitive>
                <LexemType>RussianLetter</LexemType>
                <Items>
                  <BlockItem type="ExactString">
                    <ExactString>
                      <LexemType>RussianLetter</LexemType>
                      <Value>наук</Value>
                    </ExactString>
                  </BlockItem>
                </Items>
              </Block>
            </MatchCaseItem>
          </Items>
        </MatchCase>
        <MatchCase>
          <Items>
            <MatchCaseItem type="Block">
              <Block>
                <Repeat>
                  <Minimum>1</Minimum>
                  <Maximum>1</Maximum>
                </Repeat>
                <CaseSensitive>false</CaseSensitive>
                <LexemType>RussianLetter</LexemType>
                <Items>
                  <BlockItem type="ExactString">
                    <ExactString>
                      <LexemType>RussianLetter</LexemType>
                      <Value>РАН</Value>
                    </ExactString>
                  </BlockItem>
                </Items>
              </Block>
            </MatchCaseItem>
          </Items>
        </MatchCase>
      </MatchCases>
    </Template>
  </Templates>
</Dictionary>

